{
  "by_medium": {
    "film": 55,
    "manga": 798,
    "novel": 73,
    "series": 55
  },
  "generated_at": "2026-07-05T15:04:42+00:00",
  "latest": [
    {
      "generated_at": "2026-07-05T15:04:42+00:00",
      "title_ja": "最後の証言者たち",
      "work_id": "orig:20260705150442:ec89ee26d1794c130748"
    },
    {
      "generated_at": "2026-07-05T15:04:42+00:00",
      "title_ja": "透明な放課後の逃亡者",
      "work_id": "orig:20260705150442:58945e197b7f9b21cf25"
    },
    {
      "generated_at": "2026-07-05T15:04:42+00:00",
      "title_ja": "透明な証言者たち",
      "work_id": "orig:20260705150442:cc63065a45228a147f4e"
    },
    {
      "generated_at": "2026-07-05T13:01:10+00:00",
      "title_ja": "透明な放課後の地図",
      "work_id": "orig:20260705130110:d0f01012101025734ef6"
    },
    {
      "generated_at": "2026-07-05T13:01:10+00:00",
      "title_ja": "透明な放課後の残響",
      "work_id": "orig:20260705130110:ea6104350a8ae0300fca"
    },
    {
      "generated_at": "2026-07-05T13:01:10+00:00",
      "title_ja": "眠らない放課後の逃亡者",
      "work_id": "orig:20260705130110:41dedc3f43ead5192a4f"
    },
    {
      "generated_at": "2026-07-05T11:21:33+00:00",
      "title_ja": "名前のない逃亡者",
      "work_id": "orig:20260705112133:061bbed2c8ba1ee54599"
    },
    {
      "generated_at": "2026-07-05T11:21:33+00:00",
      "title_ja": "最後の放課後の時計塔",
      "work_id": "orig:20260705112133:7fce59d6bb8817525eb9"
    },
    {
      "generated_at": "2026-07-05T11:21:33+00:00",
      "title_ja": "名前のない証言者たち",
      "work_id": "orig:20260705112133:a2868c54d6468b094f9d"
    },
    {
      "generated_at": "2026-07-05T08:35:19+00:00",
      "title_ja": "忘れられた時計塔",
      "work_id": "orig:20260705083519:c8b60b185b8cccb068ee"
    },
    {
      "generated_at": "2026-07-05T08:35:19+00:00",
      "title_ja": "名前のない証言者たち",
      "work_id": "orig:20260705083519:8eb32b940ca3b497e9f5"
    },
    {
      "generated_at": "2026-07-05T08:35:19+00:00",
      "title_ja": "逆さまの証言者たち",
      "work_id": "orig:20260705083519:21fc208829d3ace2525a"
    },
    {
      "generated_at": "2026-07-05T05:51:16+00:00",
      "title_ja": "忘れられた証言者たち",
      "work_id": "orig:20260705055116:5f522cda672809d13eb7"
    },
    {
      "generated_at": "2026-07-05T05:51:16+00:00",
      "title_ja": "眠らない放課後の逃亡者",
      "work_id": "orig:20260705055116:714666534cb6a64945ff"
    },
    {
      "generated_at": "2026-07-05T05:51:16+00:00",
      "title_ja": "名前のない放課後の地図",
      "work_id": "orig:20260705055116:e0967d89521fabaa7937"
    },
    {
      "generated_at": "2026-07-05T01:42:06+00:00",
      "title_ja": "二度目の証言者たち",
      "work_id": "orig:20260705014206:b2c091aa9cbc43e88605"
    },
    {
      "generated_at": "2026-07-05T01:42:06+00:00",
      "title_ja": "透明な証言者たち",
      "work_id": "orig:20260705014206:a0c863ad9eaf7ec5185a"
    },
    {
      "generated_at": "2026-07-05T01:42:06+00:00",
      "title_ja": "逆さまの放課後の修復士",
      "work_id": "orig:20260705014206:ff3b6a8704eedcbfcb71"
    },
    {
      "generated_at": "2026-07-04T18:49:47+00:00",
      "title_ja": "逆さまの証言者たち",
      "work_id": "orig:20260704184947:0975af252ebce8a45bf0"
    },
    {
      "generated_at": "2026-07-04T18:49:47+00:00",
      "title_ja": "透明な証言者たち",
      "work_id": "orig:20260704184947:7623f3d839d4da368778"
    }
  ],
  "total_generated_works": 981
}
